django_request_signer-5.1.4.dist-info/licenses/LICENSE
request_signer/__init__.py
request_signer/constants.py
request_signer/decorators.py
request_signer/models.py
request_signer/signals.py
request_signer/validator.py
request_signer/client/__init__.py
request_signer/client/generic/__init__.py
request_signer/client/generic/base.py
request_signer/client/generic/django_backend.py
request_signer/client/generic/django_client.py
request_signer/client/generic/rest.py
request_signer/migrations/0001_initial.py
request_signer/migrations/__init__.py
request_signer/tests/__init__.py
request_signer/tests/test_client.py
request_signer/tests/test_django_client.py
request_signer/tests/test_request.py
request_signer/tests/test_response.py
request_signer/tests/test_rest_client.py
request_signer/tests/test_signed_request.py
django_request_signer-5.1.4.dist-info/METADATA
django_request_signer-5.1.4.dist-info/WHEEL
django_request_signer-5.1.4.dist-info/top_level.txt
django_request_signer-5.1.4.dist-info/RECORD
